fssucaiot/__init__.py
fssucaiot/core.py
fssucaiot-0.1.1.dist-info/licenses/LICENSE
fssucaiot-0.1.1.dist-info/METADATA
fssucaiot-0.1.1.dist-info/WHEEL
fssucaiot-0.1.1.dist-info/top_level.txt
fssucaiot-0.1.1.dist-info/RECORD
