Metadata-Version: 2.4
Name: fssucaiot
Version: 0.1.1
Summary: 一个适用于教学的语音控制物联网模块，支持VOSK语音识别和MQTT控制
Home-page: https://github.com/yourname/fssucaiot
Author: 你的名字
Author-email: 307262079@qq.com
License: MIT
Classifier: Programming Language :: Python :: 3
Classifier: License :: OSI Approved :: MIT License
Classifier: Operating System :: OS Independent
Requires-Python: >=3.7
License-File: LICENSE
Requires-Dist: vosk
Requires-Dist: numpy
Requires-Dist: sounddevice
Requires-Dist: scipy
Requires-Dist: paho-mqtt
Dynamic: author
Dynamic: author-email
Dynamic: classifier
Dynamic: description-content-type
Dynamic: home-page
Dynamic: license
Dynamic: license-file
Dynamic: requires-dist
Dynamic: requires-python
Dynamic: summary
